dnsrewriteproxy.py
dnsrewriteproxy-0.0.16.dist-info/LICENSE
dnsrewriteproxy-0.0.16.dist-info/METADATA
dnsrewriteproxy-0.0.16.dist-info/WHEEL
dnsrewriteproxy-0.0.16.dist-info/top_level.txt
dnsrewriteproxy-0.0.16.dist-info/RECORD
