Metadata-Version: 2.1
Name: dnsrewriteproxy
Version: 0.0.16
Summary: A DNS proxy server that conditionally rewrites and filters A record requests
Home-page: https://github.com/uktrade/dns-rewrite-proxy
Author: Department for International Trade
Author-email: webops@digital.trade.gov.uk
License: UNKNOWN
Platform: UNKNOWN
Classifier: Programming Language :: Python :: 3
Classifier: License :: OSI Approved :: MIT License
Classifier: Topic :: Internet :: Name Service (DNS)
Requires-Python: >=3.7.0
Requires-Dist: aiodnsresolver (>=0.0.149)
